{
    "info": [
        {
            "year": 2002,
            "month": 5,
            "rank": 50,
            "type": "월별차트",
            "website": "Melon"
        },
        ""
    ],
    "song_id": "94296",
    "song_name": "반",
    "album": "Magic To Go To My Star",
    "release_date": "2001.10.23",
    "artist": "이정현",
    "genre": "댄스",
    "lyric_writer": "PJ",
    "composer": "김진아",
    "arranger": "PJ",
    "lyrics": {
        "row_num": 36,
        "lines": [
            "흔들리는 네 눈빛에 끌렸어",
            "애써 나를피하지는마",
            "버려졌던 기억 따윈 덮어둬",
            "이미 나도 겪어봤으니",
            "다시 한번 내게 말해봐",
            "너도 나를 사랑했다고",
            "나 역시 너 처럼 사랑이 두려워도",
            "외로운건 싫으니까",
            "반만 나를 믿어봐",
            "반만 나를 닮아봐",
            "정말 사랑하다가",
            "끝나도 후회 없도록",
            "암만 사랑해봤자",
            "뒤돌아서면 남이야",
            "어차피 이 세상에서",
            "완전한 사랑은 없어",
            "",
            "더 이상은 네게 강요하지마",
            "너 하나만 사랑할꺼야",
            "쓸데없는 욕심 따윈 버렸어",
            "이젠 나를 시험하지마",
            "사랑하진 않았었다고",
            "헤어진다 말했었지만",
            "그렇게 몰랐니 나에게 솔직해봐",
            "이젠 나를 책임져봐",
            "반만 나를 믿어봐",
            "반만 나를 닮아봐",
            "정말 사랑하다가",
            "끝나도 후회없도록",
            "암만 사랑해봤자",
            "뒤돌아서면 남이야",
            "어차피 이 세상에서 완전한 사랑은 없어",
            "나나나 나하나 땜에괜한자책 하지마",
            "괜히 미안해지고 괜한 자책감만 느껴",
            "너와나 함께할 때에 그냥 좋았던것 뿐야",
            "이젠 끝날수 없어 날 받아줘"
        ]
    }
}