{
    "info": [
        {
            "year": 2009,
            "month": 4,
            "rank": 50,
            "type": "월별차트",
            "website": "Melon"
        },
        ""
    ],
    "song_id": "2123958",
    "song_name": "보디가드 (애니콜 CF송 - 샤방 보디가드폰)",
    "album": "보디가드",
    "release_date": "2009.04.03",
    "artist": "SHINee (샤이니)",
    "genre": "댄스",
    "lyric_writer": "이재명",
    "composer": "유두호",
    "arranger": "이재명",
    "lyrics": {
        "row_num": 61,
        "lines": [
            "내 맘을 뺏은 그대",
            "내 맘을 뺏은 그대",
            "내 손을 놓지 마요",
            "나를 살려줘 SOS",
            "내가 지금 갈께",
            "슈퍼맨처럼 날아서",
            "지켜줄게",
            "이렇게 너와 함께 있으면",
            "세상 모든걸 가진 기분",
            "언제까지나 영원토록 사랑할게",
            "아침햇살 같은 너의 미소",
            "온종일 가슴이 설레여",
            "어두운 밤 내 꿈을 밝혀줘",
            "네가 힘들고 지칠때면",
            "너를 지켜줄 단 한사람",
            "나는 너의 보디가드",
            "널 지켜줄게 사랑해",
            "그 누구보다 귀여운",
            "일루미네이션 빠져버린 순간",
            "너는 내게 완벽해",
            "언제라도 나를 불러줘 달려갈게",
            "네 마음 사랑이 내게 올 수 있게",
            "잊지마 어디서든 너의 보디가드",
            "걱정마 이젠 내가 너의 마징가",
            "힘이 들 땐 이젠 내게 안겨",
            "모든걸 내게 맡겨",
            "이제는 너는 나를 믿어",
            "동화 속 주인공과 함께",
            "너를 지켜줄게",
            "만화 속 캐릭터와 함께",
            "힘이 되어줄게",
            "영원히 너를 지켜",
            "곁에 있어 줄 꺼라",
            "신 앞에 무릎 꿇고 맹세할게",
            "네가 힘들고 지칠때면",
            "너를 지켜줄 단 한사람",
            "나는 너의 보디가드",
            "널 지켜줄게 사랑해",
            "그 누구보다 귀여운",
            "일루미네이션 빠져버린 순간",
            "너는 내게 완벽해",
            "언제라도 나를 불러줘 달려갈게",
            "네 마음 사랑이 내게 올 수 있게",
            "네 앞에 다가가 당당하게",
            "눈을 감은 너에게 살짝 입맞춤",
            "사랑해",
            "나는 너의 보디가드",
            "널 지켜줄게 사랑해",
            "그 누구보다 귀여운",
            "일루미네이션 빠져버린 순간",
            "너는 내게 완벽해",
            "언제라도 나를 불러줘 달려갈게",
            "네 마음 사랑이 내게 올 수 있게",
            "나는 너의 보디가드",
            "널 지켜줄게 사랑해",
            "그 누구보다 귀여운",
            "일루미네이션 빠져버린 순간",
            "너는 내게 완벽해",
            "언제라도 나를 불러줘 달려갈게",
            "네 마음 사랑이 내게 올 수 있게",
            "love"
        ]
    }
}