{
    "info": [
        {
            "year": 2003,
            "month": 12,
            "rank": 50,
            "type": "월별차트",
            "website": "Melon"
        },
        ""
    ],
    "song_id": "465286",
    "song_name": "안녕",
    "album": "Seraphim",
    "release_date": "2003.06.17",
    "artist": "박혜경",
    "genre": "록/메탈",
    "lyric_writer": "강현민",
    "composer": "박지원",
    "arranger": "박혜경",
    "lyrics": {
        "row_num": 34,
        "lines": [
            "외로운 날들이여 모두 다 안녕",
            "내 마음속에 눈물들도 이제는 안녕 오",
            "어제의 너는 바람을 타고 멀리",
            "후회도 없이 미련없이 날아가 굿바이",
            "오오오 영원히 워오오",
            "거울에 비친 너의 모습이 슬퍼",
            "늘 웃음짓던 예전의 넌 어디에 있니",
            "저 파란 하늘 눈부신 별들도",
            "모두 다 너를 위해 있잖니",
            "더 이상 내 안에 그 일은 없던 일",
            "그래서 아픈 기억 모두 버려야 할 일",
            "눈물짓지마 새로운 오늘을",
            "맞이할 준비를 해봐 오오",
            "외로운 날들이여 모두 다 안녕",
            "내 마음속에 눈물들도 이제는 안녕 오",
            "어제의 너는 바람을 타고 멀리",
            "후회도 없이 미련없이 날아가 굿바이",
            "오오오 영원히 워오오",
            "슬프게 내린 비는 꽃을 피우고",
            "너의 눈물은 예쁜 사랑을 피울꺼야",
            "슬퍼하지마 새로운 오늘을",
            "맞이할 준비를 해봐 오오",
            "햇살 가득한 날들이여 안녕",
            "긴잠에서 날 깨워준 아침이여 안녕 오",
            "너의 유리처럼 맑은 미소가",
            "세상을 환히 웃음짓게 할꺼야 오오",
            "외로운 날들이여 모두 다 안녕",
            "내 마음속에 눈물들도 이제는 안녕 오",
            "어제의 너는 바람을 타고 멀리",
            "후회도 없이 미련없이 날아가",
            "햇살 가득한 날들이여 안녕",
            "긴잠에서 날 깨워준 아침이여 안녕 오",
            "너의 유리처럼 맑은 미소가",
            "세상을 환히 웃음짓게 할꺼야 오"
        ]
    }
}