{
    "info": [
        {
            "year": 2008,
            "month": 7,
            "rank": 50,
            "type": "월별차트",
            "website": "Melon"
        },
        ""
    ],
    "song_id": "1891606",
    "song_name": "Cute Love ('우리결혼했어요' 솔비 테마곡)",
    "album": "Cute Love",
    "release_date": "2008.06.19",
    "artist": "솔비",
    "genre": "-",
    "lyric_writer": "",
    "composer": "",
    "arranger": "",
    "lyrics": {
        "row_num": 37,
        "lines": [
            "감추려 외면하고",
            "감추려 노력을 해봐도",
            "왜 이렇게 안 되지",
            "사랑이 내게 오나봐",
            "그냥 웃음이 나고",
            "그냥 모든 게 좋아 보여",
            "아이처럼 마냥 즐겁고 행복해",
            "너를 사랑하나봐",
            "이런 내 맘을 너도 느끼죠",
            "너와 함께 있으면",
            "나도 모르게 너를 닮아가",
            "눈을 감아도",
            "내 눈 앞에는 너만 서있어",
            "나도 신기해 널 사랑하나봐",
            "매일 거울만 보고",
            "매일 너에게 보이려고",
            "인형처럼 마냥 예쁜 척 하게 돼",
            "너를 사랑하나봐",
            "이런 내 맘을 너도 느끼죠",
            "너와 함께 있으면",
            "나도 모르게 너를 닮아가",
            "눈을 감아도",
            "내 눈 앞에는 너만 서있어",
            "나도 신기해 널 사랑하나봐",
            "내가 느끼는 행복",
            "혼자만의 느낌은 아니죠",
            "이 행복 우리 둘이",
            "우리 같이 만들어가요",
            "",
            "너를 사랑하나봐",
            "이런 내 맘을 너도 느끼죠",
            "너와 함께 있으면",
            "나도 모르게 미소 짓게 돼",
            "잠이 들어도",
            "내 꿈에서는 너만 가득해",
            "you & I Fall in love 사랑해",
            "영원토록 사랑해"
        ]
    }
}