{
    "info": [
        {
            "year": 2023,
            "month": 6,
            "rank": 50,
            "type": "월별차트",
            "website": "Melon"
        },
        ""
    ],
    "song_id": "35595136",
    "song_name": "새삥 (Prod. ZICO) (Feat. 호미들)",
    "album": "스트릿 맨 파이터(SMF) Original Vol.3 (계급미션)",
    "release_date": "2022.09.06",
    "artist": "지코 (ZICO)",
    "genre": "랩/힙합",
    "lyric_writer": "지코 (ZICO)",
    "composer": "CK",
    "arranger": "Louie",
    "lyrics": {
        "row_num": 89,
        "lines": [
            "기분이 째져",
            "Ayy who's the best dresser",
            "반경 100m 누가 젤 튀어",
            "잘 되면 셀럽",
            "못 되면 평생 리셀러",
            "내 개성은 시대를 안 타 huh",
            "안 타 cause",
            "나는 새삥",
            "모든 게 다 새삥",
            "보세 옷을 걸쳐도",
            "브랜드 묻는 DM이 와",
            "I’m too sexy",
            "헌 집 주고 새집",
            "프리미엄이 붙어",
            "두 배, 세 배, 네 배 yeah",
            "나는 새삥",
            "11년째 freshman",
            "유명세를 걷어",
            "현찰 대신 스펙을 stackin’",
            "Ooh! You’re not savage",
            "남의 멋만 쌔비지",
            "난 취향을 감춰 그래",
            "내 세컨 카는 수수께끼",
            "Show and prove의 심볼",
            "넘볼 수 없는 임금",
            "The king is back 뽷!",
            "다시 ’코’시국",
            "암만 영끌해도 근본은 절대 못 사",
            "눈팅으로 배운 너의 street fashion",
            "뚜까 패고파",
            "기분이 째져",
            "Ayy who's the best dresser",
            "반경 100m 누가 젤 튀어",
            "잘 되면 셀럽",
            "못 되면 평생 리셀러",
            "내 개성은 시대를 안 타 huh",
            "안 타 cause",
            "나는 새삥",
            "모든 게 다 새삥",
            "보세 옷을 걸쳐도",
            "브랜드 묻는 DM이 와",
            "I’m too sexy",
            "헌 집 주고 새집",
            "프리미엄이 붙어",
            "두 배, 세 배, 네 배 yeah",
            "아마 나는 오늘도",
            "미치게 하겠지 workin’",
            "이유는 뻔하지 새로운 옷이",
            "알어 니 위치는 겉만 하지 마",
            "건방 빌린 게 티 나서 bro",
            "이제 여름이 오니까 준비해",
            "내 목에다 채워질 아이스체인",
            "1234 옷을 세는 것도 지겨워 man",
            "New thang",
            "I love my hates",
            "원해 new chain",
            "우리 엄만 생일마다",
            "새 가방이 생기지",
            "신기록 갱신",
            "우린 없어 배신",
            "나는 매일 새신",
            "Yessir I really came from zero",
            "그래서 2배로 work",
            "책임을 가진 삶은 생각보다 괴로워",
            "언제나 let's go hard",
            "내 옷은 새로워",
            "난 운전할 때마다 맨 앞이라 외로워",
            "안 무셔 drip check",
            "내 옷들은 늘 새삥",
            "아무도 못 말려 나란 바닥노무 쉐낀",
            "멈출 수 없어 난 쌓아야 해 stack",
            "안전모를 썼던",
            "나는 절대 못해 cap",
            "기분이 째져",
            "Ayy who's the best dresser",
            "반경 100m 누가 젤 튀어",
            "잘 되면 셀럽",
            "못 되면 평생 리셀러",
            "내 개성은 시대를 안 타 huh",
            "안 타 cause",
            "나는 새삥",
            "모든 게 다 새삥",
            "보세 옷을 걸쳐도",
            "브랜드 묻는 DM이 와",
            "I’m too sexy",
            "헌 집 주고 새집",
            "프리미엄이 붙어",
            "두 배, 세 배, 네 배 yeah",
            "나는 새삥 모든 게 다 새삥"
        ]
    }
}