{
    "info": [
        {
            "year": 2001,
            "month": 12,
            "rank": 25,
            "type": "월별차트",
            "website": "Melon"
        },
        ""
    ],
    "song_id": "32776",
    "song_name": "You're My Life",
    "album": "You're My Life",
    "release_date": "2001.09.25",
    "artist": "김민종",
    "genre": "발라드",
    "lyric_writer": "김민종",
    "composer": "조규만",
    "arranger": "조규만",
    "lyrics": {
        "row_num": 30,
        "lines": [
            "혹시 내가 달라진 것 같나요",
            "그대가 그런 건가요",
            "나는 아닌데 행복을 느끼는데",
            "그렇다고 난 믿고 있는데",
            "오늘 또 누굴 만났나봐요",
            "나를 몹시 피하는군요",
            "그런가봐요 그렇게 변하는가봐요",
            "영원한 사랑은 그저 떠도는 거짓인가요",
            "oh You're my life",
            "나에겐 텅 빈 그대 행복을 빌어야 하나요",
            "어려워요 나를 달랠 자신 없어요",
            "내 안은 그대뿐이죠",
            "",
            "다시 많은 비가 오고 있어요",
            "어제는 비를 맞았죠 괜찮았어요",
            "오히려 포근하던걸요",
            "우리의 많은 날들을 그렇게 보냈었기에",
            "oh You're my life",
            "그대 내 안에 그저 그렇게 떠돈 건 아니죠",
            "행복했던 그대 안의 나의 사랑을",
            "조금 더 간직해줘요",
            "oh You're my life",
            "",
            "더 흘릴 눈물도 더 기다릴 작은 힘도",
            "야윈 듯 잠들어 가죠 이렇게 젖은 가슴에",
            "oh You're my life",
            "나에겐 텅 빈 그대 행복을 빌어야 하나요",
            "어려워요 나를 달랠 자신 없어요",
            "내 안은 그대뿐이죠",
            "내 안은 You're my life"
        ]
    }
}