{
    "info": [
        {
            "year": 2018,
            "month": 11,
            "rank": 50,
            "type": "월별차트",
            "website": "Melon"
        },
        ""
    ],
    "song_id": "31409519",
    "song_name": "하루살이 (feat. 설리, Rad Museum)",
    "album": "하루살이 (feat. 설리, Rad Museum)",
    "release_date": "2018.11.08",
    "artist": "DEAN",
    "genre": "R&B/Soul",
    "lyric_writer": "Deanfluenza",
    "composer": "Rad Museum",
    "arranger": "말든 (Marldn)",
    "lyrics": {
        "row_num": 39,
        "lines": [
            "자연스레 떠진 눈에 담긴 넌",
            "오오 누군가요",
            "말하지 않아도 돼",
            "더 중요한 건",
            "우린 이렇게 살아있네",
            "낯선 향이 베인 옷을 던져두고",
            "어제의 기억을 씻어 내려 봐도",
            "반복돼 날 잊은 채로",
            "새빨간 핑계 뒤에 숨어",
            "몇 번을 되묻고 되물어봐도",
            "내가 나쁜 건지",
            "아니면 내가 아픈 건지",
            "밤 거리를 배회 하면서",
            "하룻밤을 기대하는 너",
            "어떤 마음으로 내 앞에 있는지",
            "그냥 다 말해줄 순 없겠니",
            "네 마음도 다를 것 없다고",
            "모두 다 똑같아 이 맘 때 즘엔",
            "당연한 건 없어 모든 인연에는",
            "우연이라해도 나만 다칠 걸",
            "바라는 건 없어",
            "오늘 이후로",
            "하루 만에 우린 이별한거야",
            "자연스레 떠진 눈에 담긴 넌",
            "오오 누군가요",
            "말하지 않아도 돼 더 중요한 건",
            "우린 이렇게 살아있네",
            "자연스레 떠진 눈에 담긴 넌",
            "오오 누군가요",
            "말하지 않아도 돼 더 중요한 건",
            "우린 이렇게 살고 있네",
            "현실을 직면하기엔 난 약해",
            "외면해보지만 그게 잘 안돼",
            "끝 없이 반복되는 하루 앞에",
            "난 죽어 있었던 거에 가깝기에",
            "진실이라는 건 아프기만 해",
            "달콤한 거짓이 내 살에 닿을 때",
            "그렇게 다시 하루를 살아 갈게",
            "이름 모를 그 밤을 잠궈 둔 채"
        ]
    }
}