{
    "info": [
        {
            "year": 2022,
            "month": 10,
            "rank": 50,
            "type": "월별차트",
            "website": "Melon"
        },
        ""
    ],
    "song_id": "35709043",
    "song_name": "그래서 그대는",
    "album": "그래서 그대는",
    "release_date": "2022.10.10",
    "artist": "이영현",
    "genre": "발라드",
    "lyric_writer": "박준배",
    "composer": "이미아",
    "arranger": "이근상",
    "lyrics": {
        "row_num": 37,
        "lines": [
            "나는 나에게",
            "길 들여지길 바래요",
            "그동안 그댈 너무 많이",
            "닮아 있었나 봐요",
            "지워질 때도 됐는데",
            "그댄 또 누군가에게 길들었나요",
            "혹시 그 사람",
            "예전 나완 많이 틀린가 봐요",
            "그래서 그대는 날 잊고 사는지",
            "내 아름다운 사람아",
            "여전히 나는 니 모습인데",
            "또 다른 사랑 배워갈 그대 가슴에",
            "내 작은 기억 하나만",
            "내 눈물 나는 사랑아",
            "같은 아픔에 머물 수 있게",
            "다른 이별에 울어도",
            "내 품 안에서",
            "그 마음 아물게 해요",
            "내가 아닌 그대 행복한가요",
            "혹시나 내 이름 벌써 잊었나요",
            "내 아름다운 사람아",
            "여전히 나는 니 모습인데",
            "또 다른 사랑 배워갈",
            "그대 가슴에",
            "내 작은 기억 하나만",
            "내 눈물 나는 사랑아",
            "같은 아픔에 머물 수 있게",
            "다른 이별에 울어도",
            "내 품 안에서",
            "그 마음 아물게 해요",
            "내 작은 기억 하나만",
            "내 눈물 나는 사랑아",
            "같은 아픔에 머물 수 있게",
            "다른 이별에 울어도",
            "내 품 안에서",
            "그 마음 아물게 해요",
            "그 마음 아물게 해요"
        ]
    }
}