{
    "info": [
        {
            "year": 2007,
            "month": 10,
            "rank": 41,
            "type": "월별차트",
            "website": "Melon"
        },
        ""
    ],
    "song_id": "1738362",
    "song_name": "남자라서 웃어요",
    "album": "김장훈의 트롯",
    "release_date": "2007.09.28",
    "artist": "김장훈",
    "genre": "성인가요/트로트",
    "lyric_writer": "Tablo",
    "composer": "Tablo",
    "arranger": "",
    "lyrics": {
        "row_num": 58,
        "lines": [
            "난 한 잔을 마시고",
            "그댈 웃으며 보냈죠",
            "또 한 잔을 마시고",
            "그저 바보처럼 웃었죠",
            "웃어도 웃지 못하는 게 삶인데",
            "남자라서 참 슬픈 세상인데",
            "나 오늘도 이 무대 위에서",
            "웃으며 크게 노래 불러요",
            "나 괜찮아요",
            "뒤돌아보지 마세요",
            "울고 싶어도 웃잖아요",
            "나 괜찮아요",
            "미안해하지 마세요",
            "죽고 싶어도 살잖아요",
            "오늘도 눈물을 마신다",
            "한 잔 술에 이별을 바친다",
            "아쉽다 모든 것이 다",
            "그리움만 남은 것인가",
            "떠나가는 너의 뒷 모습에",
            "돌아보는 것도 잊고 있을 때",
            "그래 난 남자니까",
            "웃으며 보내줄게 내 님아",
            "잊어도 잊지 못하는 게 사랑인데",
            "남자라서 참 슬픈 세상인데",
            "나 오늘도 이 무대 뒤에서",
            "웃으며 그댈 기다리네요",
            "나 괜찮아요",
            "뒤돌아보지 마세요",
            "울고 싶어도 웃잖아요",
            "나 괜찮아요",
            "미안해하지 마세요",
            "죽고 싶어도 살잖아요",
            "Come on 무대 위로 조명이 드리워",
            "나는 떠난 그녀를 그리며",
            "미소란 가면을 쓰고",
            "관객들 사이를 스치며",
            "나를 버린 그녀와 눈이 마주쳐",
            "멈칫하지만 숨을 가누며",
            "무대를 내려와 그녀를 기다려",
            "벌써 몇 시간 째",
            "오늘도 술에 취하고",
            "낯설은 여자 품에 눈을 감죠",
            "괜찮아요",
            "이젠 웃을 수 가 있어요",
            "남자라서 바보처럼 웃어요",
            "나 괜찮아요",
            "뒤돌아보지 마세요",
            "울고 싶어도 웃잖아요",
            "나 괜찮아요",
            "미안해하지 마세요",
            "죽고 싶어도",
            "어쩔 수 없이 숨 쉬며 살잖아요",
            "나 괜찮아요",
            "뒤돌아보지 마세요",
            "울고 싶어도 웃잖아요",
            "나 괜찮아요",
            "미안해하지 마세요",
            "죽고 싶어도 살잖아요"
        ]
    }
}