{
    "info": [
        {
            "year": 2019,
            "month": 8,
            "rank": 17,
            "type": "월별차트",
            "website": "Melon"
        },
        ""
    ],
    "song_id": "31879867",
    "song_name": "Snapping",
    "album": "Flourishing",
    "release_date": "2019.06.24",
    "artist": "청하",
    "genre": "댄스",
    "lyric_writer": "소라",
    "composer": "박우상",
    "arranger": "박우상",
    "lyrics": {
        "row_num": 60,
        "lines": [
            "Don’t make me love you",
            "하얗게 올라온 거품",
            "왜 자꾸 나를 보며 웃는데",
            "꿈인 걸 느끼게",
            "아쉬운 표정이 또 왜 이렇게 맴도니",
            "Really freaky 베베 꼬인 마음",
            "Doesn't matter what you baby",
            "hate or love",
            "네가 가는 길에 drop me off",
            "가볍게 take it off",
            "오늘 밤이 가기 전에 밀어내",
            "Snapping snapping 애써 눈을 가리고",
            "Snapping snapping 지친 맘을 던지고",
            "비틀대는 몸짓으로",
            "잠시 널 훔치더라도",
            "Snapping snapping I’ll let you go",
            "I know I know",
            "I don't I don't care",
            "Snapping woo snapping snapping",
            "I know I know",
            "I don't I don't mind",
            "Snapping woo snapping snapping",
            "Baby I feel you",
            "뿌옇게 번지는 퍼퓸",
            "물 같은 나를 탁하게 해 왜",
            "Shew go on fade a way",
            "번지는 purple rain",
            "또 왜 이렇게 슬프니",
            "Really freaky 베베 꼬인 마음",
            "Doesn't matter what you baby",
            "hate or love",
            "네가 가는 길에 drop me off",
            "가볍게 take it off",
            "오늘 밤이 가기 전에 밀어내",
            "Snapping snapping 애써 눈을 가리고",
            "Snapping snapping 지친 맘을 던지고",
            "비틀대는 몸짓으로",
            "잠시 널 훔치더라도",
            "Snapping snapping I’ll let you go",
            "I know I know",
            "I don't I don't care",
            "Snapping woo snapping snapping",
            "I know I know",
            "I don't I don't mind",
            "Snapping woo snapping snapping",
            "I feel so fine 난 자유로워",
            "You feel so bad 나 뿐인 넌",
            "I feel so done 이 story가 끝나",
            "When I say",
            "Snapping snapping 애써 눈을 가리고",
            "Snapping snapping 지친 맘을 던지고",
            "비틀대는 몸짓으로",
            "잠시 널 훔치더라도",
            "Snapping snapping I’ll let you go",
            "I know I know",
            "I don't I don't care",
            "Snapping woo snapping snapping",
            "I know I know",
            "I don't I don't mind",
            "Snapping woo snapping snapping"
        ]
    }
}