{
    "info": [
        {
            "year": 2006,
            "month": 6,
            "rank": 12,
            "type": "월별차트",
            "website": "Melon"
        },
        ""
    ],
    "song_id": "1199786",
    "song_name": "My Style",
    "album": "Testimony",
    "release_date": "2006.05.25",
    "artist": "업타운",
    "genre": "랩/힙합",
    "lyric_writer": "정연준",
    "composer": "스티브 김",
    "arranger": "정연준",
    "lyrics": {
        "row_num": 71,
        "lines": [
            "우리는 여자가 필요해",
            "완벽한 bODY 와 미소 띤 얼굴에",
            "부드런 목소리와 성격",
            "어딜가도 한눈에 띄어야만 합격",
            "우리는 다시 돌아온 UPTOWN",
            "이제부터 어설픈 애들은 모두 Bow Down",
            "기가 막힌 여잘끼고 우린 올라가지",
            "Hip & R&B 그것이 UPTOWN",
            "U-P-T-O-W-N",
            "We`re checking out the girl in the street again",
            "저 여자 눈이 부시네",
            "말을 걸어볼까 이렇게",
            "첫눈에 반해 버려서",
            "난 이대로 지나칠 수 없었어요",
            "내 말을 믿어준다면",
            "나와 잠시 얘기해줘요",
            "Listen Up! 더 혼자 지낼 수가 없어",
            "하루종일 X나게 거닐었어",
            "내 앞을 지나는 My Style",
            "그녈 찾았어 주저 없이 I Say 'Hello'",
            "Hello Baby 잠깐 나를 좀 봐줘요 Please",
            "My Style 그댈 기다려 왔어요 Yeah",
            "남자답게 다가왔잖아요 Ho",
            "이런 나와 함께 걸어줘요 Please",
            "너무나 Sexy한 모습으로 춤을 추는 그녀",
            "아무리 봐도 그녀만한 여잔없네",
            "쿵쿵 음악에 맞춰 뛰는 내 가슴",
            "흔들리는 그녀에게 걸어가는 One Two Step",
            "U-P-T-O-W-N",
            "We`re checking out the girl in the club again",
            "저여자 끝내주네",
            "말을 걸어볼까 이렇게",
            "Sexy한 그댈 본 후론",
            "난 그대로 다른 여잔 볼수 없었어요",
            "내말을 믿어준다면",
            "Sitting down relaxing sipping Jin",
            "",
            "뒷골목의 술취한 양아치는 따라가지 말아라",
            "남자답게 UPT가 너의 앞에 왔잖아",
            "이젠 괜찮아 날 봐라 따라와",
            "지난 일은 잊어 I`m a be OK Hello",
            "Hello Baby 혼자 있나봐요",
            "My Style나와 함께 춤을 춰요 Please",
            "남자답게 다가왔잖아요 Ho",
            "이젠 나의 손을 잡아줘요 Please",
            "That's why Korea still has no female mc",
            "That's why they called me",
            "to here from overseas",
            "I keep it gansta, UPT the MOB",
            "Jay's my name, Jay's my name",
            "You choose your destiny",
            "Now that I'm up in the game You",
            "watch me do my thang",
            "Cause someone's always tryna perpetrate I",
            "brush you off and I start to flow",
            "Someone's always gonna perpetrate",
            "Get mad and they start to hate",
            "Now that I'm up in the game I'll",
            "keep spittin' so they all don't know",
            "나의 손을 잡아",
            "(너무나 Sexy한 모습으로 춤을 추는 그녀)",
            "나의 품에 안겨",
            "(아무리 봐도 그녀만한 여잔 없네)",
            "이젠 날 따라와",
            "(You lead the way jay my name jay my name)",
            "너는 내 이상형",
            "(You're my Style Let me see that ass bounce)",
            "Hello 오늘 가지 말아줘요 Please~",
            "My style 나의 곁에 있어줘요 Please~",
            "솔직하게 Dash 하잖아요 Ho~",
            "이밤은 나와 함께 있어줘요 Yeah~"
        ]
    }
}