{
    "info": [
        {
            "year": 2007,
            "month": 4,
            "rank": 50,
            "type": "월별차트",
            "website": "Melon"
        },
        ""
    ],
    "song_id": "1615773",
    "song_name": "잊어요",
    "album": "The Sentimental Chord",
    "release_date": "2007.04.06",
    "artist": "SG 워너비",
    "genre": "R&B/Soul",
    "lyric_writer": "김영아",
    "composer": "박해운",
    "arranger": "박해운",
    "lyrics": {
        "row_num": 50,
        "lines": [
            "그만 잊어요 그만 힘들어 해요",
            "이미 그 사람 그댈 잊고서 행복할텐데",
            "늘 이렇게 아픈 그대를 보며",
            "한 걸음 다가서기도 힘겨운 나이죠",
            "내겐 누구보다 너무 고운 그대라",
            "내 맘에 품기도 아까울만큼 소중했는데",
            "그대에게 나는 너무 작아서",
            "내 어깰 빌려줄 때도",
            "그대는 사랑인걸 모르죠",
            "그만 잊어요 그만 잊어요",
            "모두 잊어버려요",
            "항상 그대의 눈물",
            "먼저 볼 수 밖에 없는 난",
            "차마 내 사랑 꺼내지도 못한 채",
            "그대 손 한 번도",
            "내 맘대로 잡아줄 수 없네요",
            "내가 있어요 내가 있어요",
            "내가 곁에 있어요",
            "항상 마음으로",
            "그대 사랑함을 외쳐보지만",
            "그대 마음까지 내가 너무 멀어서",
            "아무것도 아닌 나는",
            "늘 그대 뒤에서 그저 바라만 보죠",
            "그대 바라보면 아무 힘도 없는 나",
            "할 수만 있다면",
            "차라리 그가 되고 싶었죠",
            "술에 취해 그의 이름 부를 땐",
            "얼굴도 모르는 그가 부러워",
            "내가 싫어지네요",
            "그만 잊어요 그만 잊어요",
            "모두 잊어버려요",
            "항상 그대의 눈물",
            "먼저 볼 수 밖에 없는 난",
            "차마 내 사랑 꺼내지도 못한 채",
            "그대 손 한 번도",
            "내 맘대로 잡아줄 수 없네요",
            "내가 있어요 내가 있어요",
            "내가 곁에 있어요",
            "항상 마음으로 그대",
            "사랑함을 외쳐보지만",
            "그대 마음까지 내가 너무 멀어서",
            "아무것도 아닌 나는",
            "늘 그대 뒤에서 그저 바라만 봐요",
            "내가 있어요 내가 있어요",
            "내가 곁에 있어요",
            "항상 마음으로 그대",
            "사랑함을 외쳐보지만",
            "그대 마음까지 내가 너무 멀어서",
            "아무것도 아닌 나는",
            "늘 그대 뒤에서 그저 바라만 보죠"
        ]
    }
}