{
    "info": [
        {
            "year": 2011,
            "month": 12,
            "rank": 24,
            "type": "월별차트",
            "website": "Melon"
        },
        ""
    ],
    "song_id": "3624810",
    "song_name": "불타는 금요일 (Friday Night)",
    "album": "Dynamicduo 6th Digilog 1/2",
    "release_date": "2011.11.25",
    "artist": "다이나믹 듀오",
    "genre": "랩/힙합",
    "lyric_writer": "개코",
    "composer": "최재호",
    "arranger": "개코",
    "lyrics": {
        "row_num": 79,
        "lines": [
            "뭔가 될 것 같은 friday night",
            "do it do it doin' it right",
            "뭔가 될 것 같은",
            "friday night, friday night",
            "어오어예",
            "오늘은 불타는 friday night",
            "얘기를 만들래 오늘 밤",
            "어오어예",
            "오늘은 불타는 friday night",
            "아 몰라 오늘은 노는 날",
            "어둡고 습한 기운에",
            "무거운 기분",
            "당장 환기가 필요한 지금",
            "방전된 energy",
            "대출해줄게 my energy",
            "이자는 없어",
            "갈채와 함성으로 갚어",
            "좋은 건 나눠야 돼",
            "간보고 숨기는건 나뻐",
            "어 어차피 들통나",
            "숨기지 말아 말아",
            "뭘 더 감춰",
            "억누르지는 마",
            "막 피어오르는 뜨거운 감정",
            "오늘은 하나되자",
            "뭐 얼마나 산다고",
            "니거 내거 나눠",
            "몸 그리고 마음 내거 다 가져",
            "아끼지 말아말아 재미는 나눠",
            "뭔가 될 것 같은 friday night",
            "do it do it doin' it right",
            "뭔가 될 것 같은 friday night",
            "do it do it doin' it right",
            "어오어예",
            "We hot we hot we we we hot",
            "어오어예",
            "We hot we hot friday night",
            "심심한 사람은 여기 붙어",
            "난 만마라 만만해 여기 붙어",
            "다들 손 꼭 붙잡은 이 자리",
            "평화의 시작은 여기부터",
            "오늘은 판단을 말고",
            "있는 그대로 서로를 안아줘",
            "편견 선입견은 개집에 놔두고",
            "우리라는 두 손으로 안아줘",
            "우리는 중심 주변도 아냐 오",
            "즐거운 일부로 살자고",
            "정상에는 없는 행복이",
            "낮은 곳엔 많다고",
            "오늘은 주말이니깐",
            "불타는 주말이니깐",
            "떨어진 감정의 음정의",
            "피치 좀 올려볼까",
            "어오어예",
            "We hot we hot we we we hot",
            "어오어예",
            "We hot we hot",
            "날 똑바로 봐 니 앞에 서 있어",
            "밤새 춤추고 싶어",
            "살 것 같아",
            "I'm ready to go",
            "저 하늘위로",
            "뭔가 될 것 같은 friday night",
            "do it do it doin' it right",
            "뭔가 될 것 같은",
            "friday night friday night",
            "어오어예",
            "We hot we hot we we we hot",
            "어오어예",
            "We hot we hot",
            "scream louder yeah",
            "scream louder",
            "오늘은 불타는 friday night",
            "얘기를 만들래 오늘 밤",
            "scream louder",
            "scream louder",
            "오늘은 불타는 friday night",
            "아 몰라 오늘은 노는 날",
            "fever"
        ]
    }
}