{
    "info": [
        {
            "year": 2018,
            "month": 6,
            "rank": 50,
            "type": "월별차트",
            "website": "Melon"
        },
        ""
    ],
    "song_id": "30957524",
    "song_name": "북 (Prod. SLO)",
    "album": "고등래퍼2 팀대항전 Part.1",
    "release_date": "2018.03.17",
    "artist": "Rohann (이로한)",
    "genre": "랩/힙합",
    "lyric_writer": "Rohann (이로한)",
    "composer": "오담률",
    "arranger": "SLO (슬로)",
    "lyrics": {
        "row_num": 121,
        "lines": [
            "Asian drum ya",
            "They call it 북 ya",
            "We hit the 북 sounds like 쿵",
            "make that boom ya",
            "Bonnie and Clyde ya",
            "짝짜꿍 Umm",
            "We hit the 북 sounds like 쿵",
            "Make it new ya",
            "Asian drum ya",
            "They call it 북 ya",
            "We hit the 북 sounds like 쿵",
            "make that boom ya",
            "Bonnie and Clyde ya",
            "짝짜꿍 Umm",
            "We hit the 북 sounds like 쿵",
            "Make it new ya",
            "Woo ah",
            "북도 없이 너흰 소릴 뱉어",
            "Woo ah",
            "마치 드럼 빠진 비트 위 래퍼",
            "Woo ah",
            "우린 한국스러움의 멋을 대표",
            "Woo ah",
            "세련된 촌스러움",
            "이거지 됐어",
            "Ya 달라 억지같은",
            "멋은 버리고 새 멋을 땡겨",
            "Ya 당황스런 무대 구성을",
            "치우고 기본을 챙겨",
            "Ya 방황하는 동선",
            "누가 보기에도 멋이 없어",
            "소릴 뱉는 기본이 되는",
            "북 잡고 니들에게 보여줬어",
            "생에 흔치 않은 호흡",
            "We got a lot of swag",
            "이건 멋이고",
            "차분한 시에 랩",
            "때려박는 Unbalance",
            "이건 무엇일꼬",
            "Grrrr Kack-Kack 대신 둥둥",
            "울린 소리 Check it bae",
            "Chilla 자네 소리하게",
            "B Bastard 나 북을 치지 Man",
            "Asian drum ya",
            "They call it 북 ya",
            "We hit the 북 sounds like 쿵",
            "make that boom ya",
            "Bonnie and Clyde ya",
            "짝짜꿍 Umm",
            "We hit the 북 sounds like 쿵",
            "Make it new ya",
            "Asian drum ya",
            "They call it 북 ya",
            "We hit the 북 sounds like 쿵",
            "make that boom ya",
            "Bonnie and Clyde ya",
            "짝짜꿍 Umm",
            "We hit the 북 sounds like 쿵",
            "Make it new ya",
            "둥둥둥 Drum tap",
            "눈 풀린 채로 무댈 걸어다녀",
            "하품품품 Prrr",
            "Flexin’해도 별 감흥 없어",
            "Web B가 입은 예쁜 옷",
            "용포같아 그건 내꺼 맞아",
            "Asian bass",
            "쿵쿵",
            "총 대신 화살 장전",
            "Pew Pew Pew Pew",
            "진양조 중모리 ya",
            "중중모리 엇모리 ah",
            "자진모리하지 휘모리까지",
            "이 놀음판도 Get that 차지",
            "난 가질꺼야 너희 것도",
            "없어 버릴 것도 굿거리",
            "타고난 소리꾼의 소리",
            "막해도 박수 받아",
            "We make that",
            "마치 고수와 소리꾼 같이",
            "얼쑤 지화자",
            "다 먹을꺼야 연서와 같이",
            "자네는 북을 쳐",
            "Chilla 소리를 한다하면",
            "사람들은 가리켜",
            "You got a swag",
            "깨갱 꽹가리",
            "Dap과 다시 울리는 Bass",
            "Asian drum ya",
            "They call it 북 ya",
            "We hit the 북 sounds like 쿵",
            "make that boom ya",
            "Bonnie and Clyde ya",
            "짝짜꿍 Umm",
            "We hit the 북 sounds like 쿵",
            "Make it new ya",
            "Asian drum ya",
            "They call it 북 ya",
            "We hit the 북 sounds like 쿵",
            "make that boom ya",
            "Bonnie and Clyde ya",
            "짝짜꿍 Umm",
            "We hit the 북 sounds like 쿵",
            "Make it new ya",
            "Asian drum ya",
            "They call it 북 ya",
            "We hit the 북 sounds like 쿵",
            "make that boom ya",
            "Bonnie and Clyde ya",
            "짝짜꿍 Umm",
            "We hit the 북 sounds like 쿵",
            "Make it new ya",
            "We hit the 북",
            "We hit the 북",
            "We hit the 북",
            "We hit the 북",
            "We hit the 북",
            "We hit the 북",
            "We hit the 북",
            "We hit the 북",
            "We hit the 북 sounds like 쿵",
            "Make it new ya"
        ]
    }
}