{
    "info": [
        {
            "year": 2018,
            "month": 1,
            "rank": 50,
            "type": "월별차트",
            "website": "Melon"
        },
        ""
    ],
    "song_id": "30751158",
    "song_name": "MIC Drop (Steve Aoki Remix) (Feat. Desiigner)",
    "album": "MIC Drop (Steve Aoki Remix) (Feat. Desiigner)",
    "release_date": "2017.11.24",
    "artist": "방탄소년단",
    "genre": "랩/힙합",
    "lyric_writer": "Steve Aoki",
    "composer": "Pdogg",
    "arranger": "Supreme Boi",
    "lyrics": {
        "row_num": 119,
        "lines": [
            "Playing That Basketball",
            "We Playing That a Law",
            "Ima Just Get To The Chicken",
            "Whip it then I flip it",
            "then trap it all",
            "I gotta get to the dolla",
            "*** all them haters",
            "& back ‘em off",
            "Smoking on gas a lot",
            "Ready to wack ‘em all",
            "Wack ‘em all",
            "Wack ‘em all",
            "Clap clap clap",
            "Clap ‘em all",
            "This what I did to the haters",
            "The choppa hit ‘em tell ‘em",
            "back ‘em off",
            "She like Apple Jacks",
            "I Like Apple sauce",
            "That’s a boss",
            "That’s the cost",
            "Why you tryna flex",
            "And you fashion off",
            "Chain around my neck",
            "And her *** is soft",
            "Smoking on that gas",
            "I ain’t passing off",
            "Asthma Cough",
            "Fashion law",
            "Stash it off",
            "Dash it off",
            "Flash it off",
            "Don’t pass it off",
            "Ima just get to the chicken",
            "And trap hard hard hard",
            "With all my ***",
            "Did you see my bag",
            "Did you see my bag",
            "It's hella trophies",
            "and it's hella thick",
            "What you think bout that",
            "What you think bout that",
            "I bet it got my haters hella sick",
            "Come and follow me follow me",
            "with your signs up",
            "I'm so firin' firin' boy",
            "your time’s up",
            "Keep on and runnin' and runnin'",
            "until I catch up",
            "HOW YOU DARE",
            "HOW YOU DARE",
            "HOW YOU DARE",
            "Another trophy",
            "My hands carry 'em",
            "Too many that I can't",
            "even count 'em",
            "MIC Drop MIC Drop",
            "발발 조심 너네 말말 조심",
            "Somebody stop me",
            "I'm bouta pop off",
            "Too busy you know",
            "my body ain't enuff",
            "MIC Drop MIC Drop",
            "발발 조심 너네 말말 조심",
            "Baby watch your mouth",
            "It come back around",
            "Once upon a time",
            "We learnt how to fly",
            "Go look at your mirror",
            "Same damn clothes",
            "You know how I feel",
            "개행복",
            "How many hours do we fly",
            "I keep on dreamin' on the cloud",
            "Yeah I’m on the mountain",
            "Yeah I’m on the bay",
            "Everyday we vibin'",
            "MIC Drop Baam",
            "Did you see my bag",
            "Did you see my bag",
            "It's hella trophies",
            "and it's hella thick",
            "What you think bout that",
            "What you think bout that",
            "I bet it got my haters hella sick",
            "Come and follow me follow me",
            "with your signs up",
            "I'm so firin' firin' boy",
            "your time’s up",
            "Keep on and runnin' and runnin'",
            "until I catch up",
            "HOW YOU DARE",
            "HOW YOU DARE",
            "HOW YOU DARE",
            "Another trophy",
            "My hands carry 'em",
            "Too many that I can't",
            "even count 'em",
            "MIC Drop MIC Drop",
            "발발 조심 너네 말말 조심",
            "Somebody stop me",
            "I'm bouta pop off",
            "Too busy you know",
            "my body ain't enuff",
            "MIC Drop MIC Drop",
            "발발 조심 너네 말말 조심",
            "Haters gon' hate",
            "Players gon' play",
            "Live a life man",
            "Good luck",
            "더 볼 일 없어 마지막 인사야",
            "할 말도 없어 사과도 하지 마",
            "더 볼 일 없어 마지막 인사야",
            "할 말도 없어 사과도 하지 마",
            "잘 봐 넌 그 꼴 나지",
            "우린 탁 쏴 마치 콜라지",
            "너의 각막 깜짝 놀라지",
            "꽤 꽤 폼나지",
            "폼나지"
        ]
    }
}