{
    "info": [
        {
            "year": 2008,
            "month": 8,
            "rank": 50,
            "type": "월별차트",
            "website": "Melon"
        },
        ""
    ],
    "song_id": "1890404",
    "song_name": "Your Eyes",
    "album": "Two Things Needed For The Same Purpose And 5 Objets",
    "release_date": "2008.06.19",
    "artist": "브라운 아이즈",
    "genre": "발라드",
    "lyric_writer": "윤건",
    "composer": "윤건",
    "arranger": "",
    "lyrics": {
        "row_num": 9,
        "lines": [
            "I can see your eyes",
            "and I can see your face",
            "See your smile ever you are",
            "I can see your eyes",
            "and I can see your face",
            "See your smile ever you are",
            "I can see your eyes",
            "and I can see your face",
            "See your smile ever you are"
        ]
    }
}