{
    "info": [
        {
            "year": 2009,
            "month": 7,
            "rank": 50,
            "type": "월별차트",
            "website": "Melon"
        },
        ""
    ],
    "song_id": "2144768",
    "song_name": "Never Ending Story",
    "album": "내조의 여왕 (Digital Single)",
    "release_date": "2009.04.28",
    "artist": "윤상현",
    "genre": "발라드",
    "lyric_writer": "김태원",
    "composer": "김태원",
    "arranger": "김태원",
    "lyrics": {
        "row_num": 39,
        "lines": [
            "손댈 수 없는 저기 어딘가",
            "오늘도 넌 숨쉬고 있지만",
            "너와 머물던 작은 의자위엔",
            "같은 모습의 바람이 지나네",
            "너는 떠나면",
            "마치 날 떠나 가듯이",
            "멀리 손을 흔들며",
            "언젠가 추억에 남겨져 갈거라고",
            "그리워하면 언젠가 만나게 되는",
            "어느 영화와 같은 일들이",
            "이루어져 가기를",
            "힘겨워 한 날에",
            "너를 지킬 수 없었던",
            "아름다운 시절속에",
            "머문 그대이기에",
            "",
            "너는 떠나며 마치 날 떠나가듯이",
            "멀리 손을 흔들며",
            "언젠가 추억에 남겨져 갈거라고",
            "그리워하면 언젠가 만나게 되는",
            "어느 영화와 같은 일들이",
            "이루어져 가기를",
            "힘겨워 한 날에",
            "너를 지킬 수 없었던",
            "아름다운 시절속에 머문 그대여",
            "그리워하면 언젠가 만나게 되는",
            "어느 영화와 같은 일들이",
            "이루어져 가기를",
            "힘겨워 한 날에",
            "너를 지킬 수 없었던",
            "아름다운 시절속에",
            "머문 그대여",
            "그리워하면 언젠가 만나게 되는",
            "어느 영화와 같은 일들이",
            "이루어져 가기를",
            "힘겨워 한 날에",
            "너를 지킬 수 없었던",
            "아름다운 시절속에",
            "머문 그대이기에"
        ]
    }
}